oldmango.py
oldmangotest-0.71.dist-info/METADATA
oldmangotest-0.71.dist-info/WHEEL
oldmangotest-0.71.dist-info/entry_points.txt
oldmangotest-0.71.dist-info/top_level.txt
oldmangotest-0.71.dist-info/RECORD
